rnit_vanna/__init__.py
rnit_vanna/utils.py
rnit_vanna/base/__init__.py
rnit_vanna/base/base.py
rnit_vanna/chromadb/__init__.py
rnit_vanna/chromadb/chromadb_vector.py
rnit_vanna/exceptions/__init__.py
rnit_vanna/flask/__init__.py
rnit_vanna/flask/assets.py
rnit_vanna/flask/auth.py
rnit_vanna/openai/__init__.py
rnit_vanna/openai/openai_chat.py
rnit_vanna/openai/openai_embeddings.py
rnit_vanna/types/__init__.py
rnit_vanna_static-0.1.0.dist-info/licenses/LICENSE
rnit_vanna_static-0.1.0.dist-info/METADATA
rnit_vanna_static-0.1.0.dist-info/WHEEL
rnit_vanna_static-0.1.0.dist-info/top_level.txt
rnit_vanna_static-0.1.0.dist-info/RECORD
