Metadata-Version: 2.4
Name: rnit-vanna-static
Version: 0.1.0
Summary: Static snapshot of Vanna SQL generation library (for testing/offline use)
Home-page: https://github.com/rnit/rnit-vanna-static
Author: RNIT
Author-email: aryanrathore040@gmail.com
Keywords: sql nlp gpt openai database query natural-language
Classifier: Development Status :: 3 - Alpha
Classifier: Intended Audience :: Developers
Classifier: Topic :: Software Development :: Libraries :: Python Modules
Classifier: Topic :: Database
Classifier: Topic :: Scientific/Engineering :: Artificial Intelligence
Classifier: Programming Language :: Python :: 3
Classifier: Programming Language :: Python :: 3.7
Classifier: Programming Language :: Python :: 3.8
Classifier: Programming Language :: Python :: 3.9
Classifier: Programming Language :: Python :: 3.10
Classifier: Programming Language :: Python :: 3.11
Classifier: License :: OSI Approved :: MIT License
Classifier: Operating System :: OS Independent
Requires-Python: >=3.7
License-File: LICENSE
Requires-Dist: openai>=1.0.0
Requires-Dist: chromadb>=0.4.0
Requires-Dist: flask>=2.0.0
Requires-Dist: flask-cors>=3.0.0
Requires-Dist: pandas>=1.3.0
Requires-Dist: sqlalchemy>=1.4.0
Requires-Dist: plotly>=5.0.0
Requires-Dist: kaleido>=0.2.0
Requires-Dist: python-dotenv>=0.19.0
Dynamic: author
Dynamic: author-email
Dynamic: classifier
Dynamic: description
Dynamic: description-content-type
Dynamic: home-page
Dynamic: keywords
Dynamic: license-file
Dynamic: requires-dist
Dynamic: requires-python
Dynamic: summary
